ptype/Column.py
ptype/LR.sav
ptype/Machine.py
ptype/Machines.py
ptype/Ptype.py
ptype/PtypeCat.py
ptype/Schema.py
ptype/Trainer.py
ptype/__init__.py
ptype/__version__.py
ptype/scaler.pkl
ptype/utils.py
ptype-0.2.17.dist-info/LICENSE
ptype-0.2.17.dist-info/METADATA
ptype-0.2.17.dist-info/WHEEL
ptype-0.2.17.dist-info/top_level.txt
ptype-0.2.17.dist-info/RECORD
