Metadata-Version: 2.1
Name: ptype
Version: 0.2.17
Summary: Probabilistic type inference
Home-page: https://github.com/alan-turing-institute/ptype
Author: Taha Ceritli, Christopher K. I. Williams, James Geddes, Roly Perera
Author-email: t.y.ceritli@sms.ed.ac.uk, ckiw@inf.ed.ac.uk, jgeddes@turing.ac.uk, rperera@turing.ac.uk
License: MIT
Platform: UNKNOWN
Classifier: License :: OSI Approved :: MIT License
Classifier: License :: OSI Approved :: MIT License
Classifier: Operating System :: OS Independent
Classifier: Programming Language :: Python :: 3
Classifier: Topic :: Scientific/Engineering
Classifier: Topic :: Utilities
Requires-Python: >=3.6.0
License-File: LICENSE
Requires-Dist: greenery (>=3.2)
Requires-Dist: joblib (>=0.17.0)
Requires-Dist: matplotlib (>=3.3.0)
Requires-Dist: numpy (>=1.19.0)
Requires-Dist: pandas (>=1.1.0)
Requires-Dist: scikit-learn (>=0.24.2scipy>=1.5.0)
Provides-Extra: dev
Requires-Dist: clevercsv (>=0.6.0) ; extra == 'dev'
Requires-Dist: scikit-learn (>=0.22.0) ; extra == 'dev'
Requires-Dist: jsonpickle (>=1.4.0) ; extra == 'dev'
Requires-Dist: nbval (>=0.9.6) ; extra == 'dev'
Requires-Dist: wheel ; extra == 'dev'
Provides-Extra: docs
Requires-Dist: clevercsv (>=0.6.0) ; extra == 'docs'
Requires-Dist: scikit-learn (>=0.22.0) ; extra == 'docs'
Provides-Extra: test
Requires-Dist: jsonpickle (>=1.4.0) ; extra == 'test'
Requires-Dist: nbval (>=0.9.6) ; extra == 'test'
